archivy_git/__init__.py
archivy_static_site_gen/__init__.py
archivy_static_site_gen-0.2.4.dist-info/METADATA
archivy_static_site_gen-0.2.4.dist-info/WHEEL
archivy_static_site_gen-0.2.4.dist-info/entry_points.txt
archivy_static_site_gen-0.2.4.dist-info/top_level.txt
archivy_static_site_gen-0.2.4.dist-info/RECORD
