Metadata-Version: 2.1
Name: archivy-static-site-gen
Version: 0.2.4
Author: Uzay-G
Author-email: halcyon@disroot.org
Classifier: Programming Language :: Python :: 3
Classifier: License :: OSI Approved :: MIT License
Requires-Dist: archivy
Requires-Dist: click
Requires-Dist: lunr
